jirapt/__init__.py
jirapt/jira.py
jirapt/jira_response_iterable.py
jira_power_tools-0.2.1.dist-info/LICENSE
jira_power_tools-0.2.1.dist-info/WHEEL
jira_power_tools-0.2.1.dist-info/METADATA
jira_power_tools-0.2.1.dist-info/RECORD
