Metadata-Version: 2.1
Name: jira-power-tools
Version: 0.2.1
Summary: Tools to improve working with the python jira API.
Home-page: https://github.com/...
License: Apache-2.0
Author: David Bradford
Author-email: david.bradford@mongodb.com
Requires-Python: >=3.7,<4.0
Classifier: License :: OSI Approved :: Apache Software License
Classifier: Programming Language :: Python :: 3
Classifier: Programming Language :: Python :: 3.7
Classifier: Programming Language :: Python :: 3.8
Requires-Dist: jira (>=2.0.0,<3.0.0)
Project-URL: Repository, https://github.com/...
